drdictaphone/__init__.py
drdictaphone/audio_feedback.py
drdictaphone/audio_tools.py
drdictaphone/beep.py
drdictaphone/chat_gpt.py
drdictaphone/cli-process.py
drdictaphone/cli.py
drdictaphone/cli_client.py
drdictaphone/client.py
drdictaphone/client_commands.py
drdictaphone/client_main.py
drdictaphone/client_ui.py
drdictaphone/config/openai_api_key
drdictaphone/config.py
drdictaphone/cost_counter.py
drdictaphone/file_input.py
drdictaphone/find_ffmpeg.py
drdictaphone/gpt_model/gpt-3.5-stable.yaml
drdictaphone/gpt_model/gpt-4-stable.yaml
drdictaphone/gpt_model/gpt-4-turbo.yaml
drdictaphone/install.py
drdictaphone/instructions/post_process.yaml
drdictaphone/logger.py
drdictaphone/logger_config.py
drdictaphone/main.py
drdictaphone/microphone.py
drdictaphone/model/__init__.py
drdictaphone/model/context.py
drdictaphone/model/exchange.py
drdictaphone/model/gpt_model.py
drdictaphone/model/instructions.py
drdictaphone/model/options.py
drdictaphone/model/profile.py
drdictaphone/model/tools.py
drdictaphone/outlet.py
drdictaphone/output.py
drdictaphone/output_command.py
drdictaphone/pipeline.py
drdictaphone/pipeline_events.py
drdictaphone/post_processor/default.yaml
drdictaphone/post_processor.py
drdictaphone/profile/default.yaml
drdictaphone/profile_manager.py
drdictaphone/read_context.py
drdictaphone/server.py
drdictaphone/server_main.py
drdictaphone/server_pipeline.py
drdictaphone/static_vad.py
drdictaphone/status_aggregator.py
drdictaphone/status_manager.py
drdictaphone/tools/default.yaml
drdictaphone/tools/post_process.yaml
drdictaphone/transcriber.py
drdictaphone-0.9.6.dist-info/LICENSE
drdictaphone-0.9.6.dist-info/METADATA
drdictaphone-0.9.6.dist-info/WHEEL
drdictaphone-0.9.6.dist-info/RECORD
