Metadata-Version: 2.1
Name: DrDictaphone
Version: 0.9.6
Summary: Dictation app for the terminal and Neovim
License: LICENSE
Author: Ole Kliemann
Author-email: mail@olekliemann.de
Requires-Python: >=3.10
Classifier: Development Status :: 4 - Beta
Classifier: Intended Audience :: Developers
Classifier: Intended Audience :: End Users/Desktop
Classifier: License :: OSI Approved :: Apache Software License
Classifier: License :: Other/Proprietary License
Classifier: Operating System :: OS Independent
Classifier: Programming Language :: Python :: 3
Classifier: Programming Language :: Python :: 3.10
Classifier: Programming Language :: Python :: 3.11
Classifier: Programming Language :: Python :: 3.12
Classifier: Topic :: Text Processing
Requires-Dist: MrEventLoop (>=0.6.2)
Requires-Dist: aiofiles (>=23.2.1)
Requires-Dist: drdictaphone-shared (==0.9.3)
Requires-Dist: numpy (>=1.26.0)
Requires-Dist: openai (>=1.6.1)
Requires-Dist: prompt-toolkit (>=3.0.43)
Requires-Dist: pydantic (>=2.5.3)
Requires-Dist: pydub (==0.25.1)
Requires-Dist: python-dotenv (>=1.0.0)
Requires-Dist: pyyaml (>=6.0.2,<7.0.0)
Requires-Dist: sounddevice (>=0.4.6)
